CA lab2/CA lab2.srcs/sources_1/new/RegisterFile.v
`timescale 1ns / 1ps
//////////////////////////////////////////////////////////////////////////////////
// Company: 
// Engineer: 
// 
// Create Date: 02/24/2026 09:41:44 AM
// Design Name: 
// Module Name: RegisterFile
// Project Name: 
// Target Devices: 
// Tool Versions: 
// Description: 
// 
// Dependencies: 
// 
// Revision:
// Revision 0.01 - File Created
// Additional Comments:
// 
//////////////////////////////////////////////////////////////////////////////////

module RegisterFile (
    input  wire clk,
    input  wire rst,          
    input  wire WriteEnable,
    input  wire [4:0]  WriteReg,
    input  wire [31:0] WriteData,
    input  wire [4:0]  ReadReg1,
    output wire [31:0] ReadData1,
    input  wire [4:0]  ReadReg2,
    output wire [31:0] ReadData2
);

    // 32 registers, each 32 bits
    reg [31:0] regs [31:0];
    integer i;

    // reset + write
    always @(posedge clk) begin
        if (rst) begin
            for (i = 0; i < 32; i = i + 1)
                regs[i] <= 32'b0;
        end else if (WriteEnable && (WriteReg != 5'd0)) begin
            regs[WriteReg] <= WriteData;
        end
    end

    // x0 always reads as 0 
    assign ReadData1 = (ReadReg1 == 5'd0) ? 32'b0 : regs[ReadReg1];
    assign ReadData2 = (ReadReg2 == 5'd0) ? 32'b0 : regs[ReadReg2];

endmodule

CA lab2/CA lab2.srcs/sources_1/new/RegisterFile_tb.v
`timescale 1ns / 1ps
//////////////////////////////////////////////////////////////////////////////////
// Company: 
// Engineer: 
// 
// Create Date: 03/03/2026 10:13:22 AM
// Design Name: 
// Module Name: RegisterFile_tb
// Project Name: 
// Target Devices: 
// Tool Versions: 
// Description: 
// 
// Dependencies: 
// 
// Revision:
// Revision 0.01 - File Created
// Additional Comments:
// 
//////////////////////////////////////////////////////////////////////////////////

module RegisterFile_tb;
    reg clk;
    reg rst;
    reg WriteEnable;
    reg [4:0] WriteReg;
    reg [31:0] WriteData;
    reg [4:0] ReadReg1;
    reg [4:0] ReadReg2;
    wire [31:0] ReadData1;
    wire [31:0] ReadData2;

    RegisterFile regf_inst (
        .clk(clk), 
        .rst(rst),
        .WriteEnable(WriteEnable),
        .WriteReg(WriteReg), 
        .WriteData(WriteData),
        .ReadReg1(ReadReg1), 
        .ReadData1(ReadData1),
        .ReadReg2(ReadReg2), 
        .ReadData2(ReadData2)
    );

    initial clk = 0;
    always #5 clk = ~clk;

    initial begin
        $dumpfile("RegisterFile_tb.vcd");
        $dumpvars(0, RegisterFile_tb);

        // Initialize + Reset
        rst = 1; WriteEnable = 0; WriteReg = 0; WriteData = 0;
        ReadReg1 = 0; ReadReg2 = 0;
        #10; rst = 0; #10;

        // Writes x5 = 0xDEADBEEF, read back next cycle
        WriteEnable = 1; WriteReg = 5'd5; WriteData = 32'hDEADBEEF;
        ReadReg1 = 5'd5;
        #10;
        WriteEnable = 0;
        #10;

        // Write to x0, must remain 0
        WriteEnable = 1; WriteReg = 5'd0; WriteData = 32'hCAFEBABE;
        ReadReg1 = 5'd0;
        #10; WriteEnable = 0; #10;

        // Write x1 and x2, read simultaneously
        WriteEnable = 1; WriteReg = 5'd1; WriteData = 32'hAAAAAAAA; #10;
        WriteReg = 5'd2; WriteData = 32'h55555555; #10;
        WriteEnable = 0;
        ReadReg1 = 5'd1; ReadReg2 = 5'd2;
        #10;

        // Overwrite x5 with 0x12345678
        WriteEnable = 1; WriteReg = 5'd5; WriteData = 32'h12345678;
        ReadReg1 = 5'd5;
        #10; WriteEnable = 0; #10;

        //  Reset clears registers
        rst = 1; #10; rst = 0;
        ReadReg1 = 5'd1; ReadReg2 = 5'd2;
        #10;

        #20 $finish;
    end
endmodule

CA lab2/CA lab2.sim/sim_1/behav/xsim/RegisterFile_tb.vcd
$date
   Tue Mar  3 23:27:27 2026
$end
$version
  2020.1
$end
$timescale
  1ps
$end
$scope module RegisterFile_tb $end
$var reg 1 ! clk $end
$var reg 1 " rst $end
$var reg 1 # WriteEnable $end
$var reg 5 $ WriteReg [4:0] $end
$var reg 32 % WriteData [31:0] $end
$var reg 5 & ReadReg1 [4:0] $end
$var reg 5 ' ReadReg2 [4:0] $end
$var wire 32 ( ReadData1 [31:0] $end
$var wire 32 ) ReadData2 [31:0] $end
$scope module regf_inst $end
$var wire 1 * clk $end
$var wire 1 + rst $end
$var wire 1 , WriteEnable $end
$var wire 5 - WriteReg [4:0] $end
$var wire 32 . WriteData [31:0] $end
$var wire 5 / ReadReg1 [4:0] $end
$var wire 32 ( ReadData1 [31:0] $end
$var wire 5 0 ReadReg2 [4:0] $end
$var wire 32 ) ReadData2 [31:0] $end
$var integer 32 1 i $end
$upscope $end
$upscope $end
$enddefinitions $end
#0
$dumpvars
0!
1"
0#
b0 $
b0 %
b0 &
b0 '
b0 (
b0 )
0*
1+
0,
b0 -
b0 .
b0 /
b0 0
bx 1
$end
#5000
1!
1*
#10000
0!
0"
0*
0+
#15000
1!
1*
#20000
0!
1#
b101 $
b11011110101011011011111011101111 %
b101 &
0*
1,
b101 -
b11011110101011011011111011101111 .
b101 /
#25000
1!
b11011110101011011011111011101111 (
1*
#30000
0!
0#
0*
0,
#35000
1!
1*
#40000
0!
1#
b0 $
b11001010111111101011101010111110 %
b0 &
b0 (
0*
1,
b0 -
b11001010111111101011101010111110 .
b0 /
#45000
1!
1*
#50000
0!
0#
0*
0,
#55000
1!
1*
#60000
0!
1#
b1 $
b10101010101010101010101010101010 %
0*
1,
b1 -
b10101010101010101010101010101010 .
#65000
1!
1*
#70000
0!
b10 $
b1010101010101010101010101010101 %
0*
b10 -
b1010101010101010101010101010101 .
#75000
1!
1*
#80000
0!
0#
b1 &
b10 '
b10101010101010101010101010101010 (
b1010101010101010101010101010101 )
0*
0,
b1 /
b10 0
#85000
1!
1*
#90000
0!
1#
b101 $
b10010001101000101011001111000 %
b101 &
b11011110101011011011111011101111 (
0*
1,
b101 -
b10010001101000101011001111000 .
b101 /
#95000
1!
b10010001101000101011001111000 (
1*
#100000
0!
0#
0*
0,
#105000
1!
1*
#110000
0!
1"
0*
1+
#115000
1!
b0 (
b0 )
1*
#120000
0!
0"
b1 &
b10 '
0*
0+
b1 /
