CA lab2/CA lab2.srcs/sources_1/new/mux2.v
`timescale 1ns / 1ps
//////////////////////////////////////////////////////////////////////////////////
// Company: 
// Engineer: 
// 
// Create Date: 03/31/2026 11:42:22 PM
// Design Name: 
// Module Name: mux2
// Project Name: 
// Target Devices: 
// Tool Versions: 
// Description: 
// 
// Dependencies: 
// 
// Revision:
// Revision 0.01 - File Created
// Additional Comments:
// 
//////////////////////////////////////////////////////////////////////////////////


module mux2 (
    input  wire [31:0] in0, // input 0: PC + 4
    input  wire [31:0] in1, // input 1: branch target
    input  wire sel,   // PCSrc control signal
    output wire [31:0] out // selected next PC
);

    assign out = (sel) ? in1 : in0;

endmodule

CA lab2/CA lab2.srcs/sources_1/new/branchAdder.v
`timescale 1ns / 1ps
//////////////////////////////////////////////////////////////////////////////////
// Company: 
// Engineer: 
// 
// Create Date: 03/31/2026 11:26:17 PM
// Design Name: 
// Module Name: branchAdder
// Project Name: 
// Target Devices: 
// Tool Versions: 
// Description: 
// 
// Dependencies: 
// 
// Revision:
// Revision 0.01 - File Created
// Additional Comments:
// 
//////////////////////////////////////////////////////////////////////////////////


module branchAdder (
    input  wire [31:0] PC,
    input  wire [31:0] imm,
    output wire [31:0] branchTarget
);
    // immGen already includes the LSB 0 for B-type and J-type.
    // Do NOT shift again here - just add directly.
    assign branchTarget = PC + imm;
 
endmodule

CA lab2/CA lab2.srcs/sources_1/new/immGen.v
`timescale 1ns / 1ps
//////////////////////////////////////////////////////////////////////////////////
// Company: 
// Engineer: 
// 
// Create Date: 03/31/2026 11:47:10 PM
// Design Name: 
// Module Name: immGen
// Project Name: 
// Target Devices: 
// Tool Versions: 
// Description: 
// 
// Dependencies: 
// 
// Revision:
// Revision 0.01 - File Created
// Additional Comments:
// 
//////////////////////////////////////////////////////////////////////////////////


// immGen: handles all RISC-V immediate formats
// For B-type and J-type: bit[0] is hardcoded 0 (already *2)
// branchAdder and jumpTarget must NOT shift again
module immGen (
    input  wire [31:0] instruction,
    output reg  [31:0] imm
);
    wire [6:0] opcode = instruction[6:0];

    always @(*) begin
        case (opcode)
            // I-type: ADDI, LW, JALR
            7'b0010011,
            7'b0000011,
            7'b1100111: imm = {{20{instruction[31]}}, instruction[31:20]};

            // S-type: SW
            7'b0100011: imm = {{20{instruction[31]}},
                                instruction[31:25],
                                instruction[11:7]};

            // B-type: BEQ, BNE - LSB is already 0 (byte 1 granularity)
            7'b1100011: imm = {{19{instruction[31]}},
                                instruction[31],
                                instruction[7],
                                instruction[30:25],
                                instruction[11:8],
                                1'b0};

            // J-type: JAL - LSB already 0
            7'b1101111: imm = {{11{instruction[31]}},
                                instruction[31],
                                instruction[19:12],
                                instruction[20],
                                instruction[30:21],
                                1'b0};

            // U-type: LUI
            7'b0110111: imm = {instruction[31:12], 12'b0};

            default: imm = 32'b0;
        endcase
    end
endmodule

CA lab2/CA lab2.srcs/sources_1/new/pcAdder.v
`timescale 1ns / 1ps
//////////////////////////////////////////////////////////////////////////////////
// Company: 
// Engineer: 
// 
// Create Date: 03/31/2026 11:25:12 PM
// Design Name: 
// Module Name: pcAdder
// Project Name: 
// Target Devices: 
// Tool Versions: 
// Description: 
// 
// Dependencies: 
// 
// Revision:
// Revision 0.01 - File Created
// Additional Comments:
// 
//////////////////////////////////////////////////////////////////////////////////


module pcAdder (
    input wire [31:0] PC,       
    output wire [31:0] PC_plus4 
);

    assign PC_plus4 = PC + 32'd4;

endmodule

CA lab2/CA lab2.srcs/sources_1/new/program_counter.v
`timescale 1ns / 1ps
//////////////////////////////////////////////////////////////////////////////////
// Company: 
// Engineer: 
// 
// Create Date: 03/31/2026 11:17:07 PM
// Design Name: 
// Module Name: program_counter
// Project Name: 
// Target Devices: 
// Tool Versions: 
// Description: 
// 
// Dependencies: 
// 
// Revision:
// Revision 0.01 - File Created
// Additional Comments:
// 
//////////////////////////////////////////////////////////////////////////////////

module program_counter(
    input  wire        clk,
    input  wire        rst,
    input  wire [31:0] nextPC,
    output reg  [31:0] PC
);
    always @(posedge clk or posedge rst) begin
        if (rst) PC <= 32'b0;
        else     PC <= nextPC;
    end
endmodule




//module program_counter(
//    input  wire clk,
//    input  wire rst,
//    input  wire [31:0] nextPC,
//    output reg  [31:0] PC
//);
//    initial begin
//        PC = 32'b0;  
//    end
    
//    always @(posedge clk) begin
//        if (rst)
//            PC <= 32'b0;
//        else
//            PC <= nextPC;
//    end
//endmodule

CA lab2/CA lab2.srcs/sources_1/new/tb_infra.v
`timescale 1ns / 1ps
//////////////////////////////////////////////////////////////////////////////////
// Company: 
// Engineer: 
// 
// Create Date: 04/01/2026 09:15:48 AM
// Design Name: 
// Module Name: tb_infra
// Project Name: 
// Target Devices: 
// Tool Versions: 
// Description: 
// 
// Dependencies: 
// 
// Revision:
// Revision 0.01 - File Created
// Additional Comments:
// 
//////////////////////////////////////////////////////////////////////////////////


module tb_infra;

    reg         clk, rst, PCSrc;
    reg  [31:0] instruction;

    wire [31:0] PC, nextPC, PC_plus4, branchTarget, imm;

    program_counter pc_inst (
        .clk(clk), .rst(rst),
        .nextPC(nextPC), .PC(PC)
    );

    pcAdder pc_add (
        .PC(PC), .PC_plus4(PC_plus4)
    );

    immGen imm_gen (
        .instruction(instruction), .imm(imm)
    );

    branchAdder br_add (
        .PC(PC), .imm(imm), .branchTarget(branchTarget)
    );

    mux2 pc_mux (
        .in0(PC_plus4), .in1(branchTarget),
        .sel(PCSrc), .out(nextPC)
    );

    initial clk = 0;
    always #5 clk = ~clk;

    initial begin
        $dumpfile("tb_infra.vcd");
        $dumpvars(0, tb_infra);

        // Initialize
        rst = 1; 
        PCSrc = 0; 
        instruction = 32'b0;
        
        // Hold reset for 2 clock cycles to ensure proper initialization
        repeat(2) @(posedge clk);
        rst = 0;
        
        @(posedge clk);

        // Test 1: Sequential - PC increments by 4 each cycle
        PCSrc = 0; 
        instruction = 32'b0;
        repeat(4) @(posedge clk);

        // Test 2: Branch taken - BEQ with offset +8
        instruction = 32'h00000463;
        PCSrc = 1;
        @(posedge clk);

        // Test 3: I-type imm = +15
        PCSrc = 0;
        instruction = 32'h00F00093;
        @(posedge clk);

        // Test 4: I-type imm = -1
        instruction = 32'hFFF00093;
        @(posedge clk);

        // Test 5: S-type imm = +8
        instruction = 32'h00112423;
        @(posedge clk);

        #20; 
        $finish;
    end

endmodule

CA lab2/CA lab2.sim/sim_1/behav/xsim/tb_infra.vcd
$date
   Fri Apr  3 23:10:39 2026
$end
$version
  2020.1
$end
$timescale
  1ps
$end
$scope module tb_infra $end
$var reg 1 ! clk $end
$var reg 1 " rst $end
$var reg 1 # PCSrc $end
$var reg 32 $ instruction [31:0] $end
$var wire 32 % PC [31:0] $end
$var wire 32 & nextPC [31:0] $end
$var wire 32 ' PC_plus4 [31:0] $end
$var wire 32 ( branchTarget [31:0] $end
$var wire 32 ) imm [31:0] $end
$scope module pc_inst $end
$var wire 1 * clk $end
$var wire 1 + rst $end
$var wire 32 & nextPC [31:0] $end
$var reg 32 , PC [31:0] $end
$upscope $end
$scope module pc_add $end
$var wire 32 % PC [31:0] $end
$var wire 32 ' PC_plus4 [31:0] $end
$upscope $end
$scope module imm_gen $end
$var wire 32 - instruction [31:0] $end
$var reg 32 . imm [31:0] $end
$var wire 7 / opcode [6:0] $end
$upscope $end
$scope module br_add $end
$var wire 32 % PC [31:0] $end
$var wire 32 ) imm [31:0] $end
$var wire 32 ( branchTarget [31:0] $end
$upscope $end
$scope module pc_mux $end
$var wire 32 ' in0 [31:0] $end
$var wire 32 ( in1 [31:0] $end
$var wire 1 0 sel $end
$var wire 32 & out [31:0] $end
$upscope $end
$upscope $end
$enddefinitions $end
#0
$dumpvars
0!
1"
0#
b0 $
b0 %
b100 &
b100 '
b0 (
b0 )
0*
1+
b0 ,
b0 -
b0 .
b0 /
00
$end
#5000
1!
1*
b0 ,
#10000
0!
0*
#15000
1!
0"
b100 %
b1000 &
b1000 '
b100 (
1*
0+
b100 ,
#20000
0!
0*
#25000
1!
b0 $
b1000 %
b1100 &
b1100 '
b1000 (
1*
b1000 ,
#30000
0!
0*
#35000
1!
b1100 %
b10000 &
b10000 '
b1100 (
1*
b1100 ,
#40000
0!
0*
#45000
1!
b10000 %
b10100 &
b10100 '
b10000 (
1*
b10000 ,
#50000
0!
0*
#55000
1!
b10100 %
b11000 &
b11000 '
b10100 (
1*
b10100 ,
#60000
0!
0*
#65000
1!
1#
b10001100011 $
b11000 %
b101000 &
b11100 '
b101000 (
b1000 )
1*
b11000 ,
b10001100011 -
b1000 .
b1100011 /
10
#70000
0!
0*
#75000
1!
0#
b111100000000000010010011 $
b101000 %
b101100 &
b101100 '
b1000110 (
b1111 )
1*
b101000 ,
b111100000000000010010011 -
b1111 .
b10011 /
00
#80000
0!
0*
#85000
1!
b11111111111100000000000010010011 $
b101100 %
b110000 &
b110000 '
b101010 (
b11111111111111111111111111111111 )
1*
b101100 ,
b11111111111100000000000010010011 -
b11111111111111111111111111111111 .
#90000
0!
0*
#95000
1!
b100010010010000100011 $
b110000 %
b110100 &
b110100 '
b1000000 (
b1000 )
1*
b110000 ,
b100010010010000100011 -
b1000 .
b100011 /
#100000
0!
0*
#105000
1!
b110100 %
b111000 &
b111000 '
b1000100 (
1*
b110100 ,
#110000
0!
0*
#115000
1!
b111000 %
b111100 &
b111100 '
b1001000 (
1*
b111000 ,
